echo_lang/__init__.py
echo_lang-1.0.6.dist-info/METADATA
echo_lang-1.0.6.dist-info/WHEEL
echo_lang-1.0.6.dist-info/top_level.txt
echo_lang-1.0.6.dist-info/RECORD
