Metadata-Version: 2.1
Name: echo-lang
Version: 1.0.6
Summary: A code os.
Home-page: https://github.com/elemental9/Echo
Author: elemental9
License: Apache Software License
Platform: UNKNOWN
Classifier: Development Status :: 4 - Beta
Classifier: Intended Audience :: Developers
Classifier: License :: OSI Approved :: Apache Software License
Classifier: Natural Language :: English
Classifier: Programming Language :: Python
Classifier: Operating System :: OS Independent
Classifier: Topic :: Software Development :: Libraries :: Python Modules
Requires-Dist: quilt-lang (~=0.11.1)
